{
 "$schema": "https://schema.management.azure.com/schemas/2015-01-01/deploymentParameters.json#",
 "contentVersion": "1.0.0.0",
 "parameters": {
  "Flag0Value": {
   "value": "2fFE05Ecc18c4Ddb5fDA4790E"
  },
  "Flag1Value": {
   "value": "0006Cdf2859246cae8fDfD7ef"
  },
  "Flag2Value": {
   "value": "Be9fFE71D4CFefEbB56cdA1eF"
  },
  "Flag3Value": {
   "value": "aF76aBE22144C1EeaCf4cAbE2"
  },
  "Flag4Value": {
   "value": "6c2E57c86c2ea6e13Cbb4E3C1"
  },
  "Flag5Value": {
   "value": "eAeF698dF9fc730CdbFA95Df9"
  },
  "Flag6Value": {
   "value": "e603605F82AC698d54AC3ca7F"
  },
  "Flag7Value": {
   "value": "B25cfC3bdf9E7e4B9eE66c497"
  },
  "Flag8Value": {
   "value": "56C93dE08AFAaf4C6d7292D6E"
  },
  "Flag9Value": {
   "value": "F61D6f372DCCaD585Ac6ddf3e"
  }
 }
}